openwakeword/__init__.py
openwakeword/custom_verifier_model.py
openwakeword/data.py
openwakeword/metrics.py
openwakeword/model.py
openwakeword/train.py
openwakeword/utils.py
openwakeword/vad.py
private_assistant_openwakeword-0.6.0.dist-info/LICENSE
private_assistant_openwakeword-0.6.0.dist-info/METADATA
private_assistant_openwakeword-0.6.0.dist-info/WHEEL
private_assistant_openwakeword-0.6.0.dist-info/top_level.txt
private_assistant_openwakeword-0.6.0.dist-info/RECORD
